HelloWorld/HelloWorld.py
HelloWorld/__init__.py
HelloWorld/test.py
vittascience-0.0.1.dist-info/LICENSE
vittascience-0.0.1.dist-info/METADATA
vittascience-0.0.1.dist-info/WHEEL
vittascience-0.0.1.dist-info/top_level.txt
vittascience-0.0.1.dist-info/RECORD
