Metadata-Version: 2.1
Name: vittascience
Version: 0.0.1
Summary: This is a test package for Vittascience's Python interface.
Home-page: https://github.com/pypa/sampleproject
Author: Maxence Marchal
Author-email: maxence@vittascience.com
License: UNKNOWN
Platform: UNKNOWN
Classifier: Programming Language :: Python :: 3
Classifier: License :: OSI Approved :: MIT License
Classifier: Operating System :: OS Independent
Requires-Python: >=3.6
